pyopa/__init__.py
pyopa/aligner.py
pyopa/backend/__init__.py
pyopa/backend/cpyopa.pxd
pyopa/backend/pyopa.c
pyopa/backend/pyopa.cpython-311-x86_64-linux-musl.so
pyopa/backend/pyopa.pyx
pyopa/matrices/jtt.dat
pyopa/matrices/json/all_matrices.json
pyopa/matrices/json/logPAM1.json
pyopa/matrices/json/logPAM1_unscaled.json
pyopa-0.8.6.dist-info/METADATA
pyopa-0.8.6.dist-info/WHEEL
pyopa-0.8.6.dist-info/top_level.txt
pyopa-0.8.6.dist-info/RECORD
pyopa-0.8.6.dist-info/licenses/LICENSE
