Metadata-Version: 2.1
Name: pyopa
Version: 0.8.6
Summary: PyOPA - optimal pairwise sequence alignments
Home-page: http://omabrowser.org/
Author: OMA Browser
Author-email: contact@omabrowser.org
License: MPL 2.0
Keywords: sequence alignments Smith-Waterman Needleman-Wunsch dynamic programming bioinformatics
Classifier: Development Status :: 3 - Alpha
Classifier: Intended Audience :: Developers
Classifier: Intended Audience :: Science/Research
Classifier: Topic :: Scientific/Engineering :: Bio-Informatics
Classifier: License :: OSI Approved :: Mozilla Public License 2.0 (MPL 2.0)
Classifier: Programming Language :: Python :: 3
Classifier: Programming Language :: Python :: 3.6
Classifier: Programming Language :: Python :: 3.7
Classifier: Programming Language :: Python :: 3.8
Classifier: Programming Language :: Python :: 3.9
Classifier: Programming Language :: Python :: 3.10
Classifier: Programming Language :: Python :: 3.11
Classifier: Programming Language :: Python :: 3.12
Classifier: Programming Language :: Python :: 3.13
License-File: LICENSE
Requires-Dist: numpy
